<rules>
	<learningObjects>
		<learningObject>
			<duration>10</duration>
			<identifier>Identifier-0</identifier>
			<competencies>
				<string>object-0</string>
				<string>object-1</string>
			</competencies>
		</learningObject>

		<learningObject>
			<duration>10</duration>
			<identifier>Identifier-1</identifier>
			<competencies>
				<string>object-2</string>
			</competencies>
		</learningObject>

		<learningObject>
			<duration>10</duration>
			<identifier>Identifier-2</identifier>
			<competencies>
				<string>object-3</string>
			</competencies>
		</learningObject>

		<learningObject>
			<duration>10</duration>
			<identifier>Identifier-3</identifier>
			<constraints>
				<string>object-0</string>
				<string>object-1</string>
				<string>object-3</string>
			</constraints>
			<competencies>
				<string>object-4</string>
				<string>object-5</string>
				<string>object-6</string>
			</competencies>
		</learningObject>

		<learningObject>
			<duration>10</duration>
			<identifier>Identifier-4</identifier>
			<constraints>
				<string>object-4</string>
				<string>object-6</string>
			</constraints>
			<competencies>
				<string>object-7</string>
				<string>object-8</string>
				<string>object-9</string>
			</competencies>
		</learningObject>

		<learningObject>
			<duration>10</duration>
			<identifier>Identifier-5</identifier>
			<constraints>
				<string>object-9</string>
			</constraints>
			<competencies>
				<string>object-10</string>
				<string>object-11</string>
			</competencies>
		</learningObject>

		<learningObject>
			<duration>10</duration>
			<identifier>Identifier-6</identifier>
			<constraints>
				<string>object-7</string>
				<string>object-11</string>
				<string>object-10</string>
			</constraints>
			<competencies>
				<string>object-12</string>
				<string>object-13</string>
			</competencies>
		</learningObject>

		<learningObject>
			<duration>10</duration>
			<identifier>Identifier-7</identifier>
			<constraints>
				<string>object-5</string>
				<string>object-13</string>
			</constraints>
			<competencies>
				<string>object-14</string>
				<string>object-15</string>
			</competencies>
		</learningObject>

		<learningObject>
			<duration>10</duration>
			<identifier>Identifier-8</identifier>
			<constraints>
				<string>object-12</string>
				<string>object-2</string>
			</constraints>
			<competencies>
				<string>object-16</string>
			</competencies>
		</learningObject>

		<learningObject>
			<duration>10</duration>
			<identifier>Identifier-9</identifier>
			<constraints>
				<string>object-16</string>
				<string>object-8</string>
			</constraints>
			<competencies>
				<string>object-17</string>
			</competencies>
		</learningObject>

		<learningObject>
			<duration>10</duration>
			<identifier>Identifier-10</identifier>
			<constraints>
				<string>object-15</string>
				<string>object-14</string>
			</constraints>
			<competencies>
				<string>object-18</string>
			</competencies>
		</learningObject>

		<learningObject>
			<duration>10</duration>
			<identifier>Identifier-11</identifier>
			<constraints>
				<string>object-18</string>
				<string>object-17</string>
			</constraints>
			<competencies>
				<string>object-19</string>
				<string>object-20</string>
				<string>object-21</string>
			</competencies>
		</learningObject>

		<learningObject>
			<duration>10</duration>
			<identifier>Identifier-12</identifier>
			<constraints>
				<string>object-21</string>
				<string>object-19</string>
				<string>object-20</string>
			</constraints>
			<competencies>
				<string>object-22</string>
				<string>object-23</string>
				<string>object-24</string>
			</competencies>
		</learningObject>

		<learningObject>
			<duration>10</duration>
			<identifier>Identifier-13</identifier>
			<constraints>
				<string>object-23</string>
			</constraints>
			<competencies>
				<string>object-25</string>
			</competencies>
		</learningObject>

		<learningObject>
			<duration>10</duration>
			<identifier>Identifier-14</identifier>
			<constraints>
				<string>object-24</string>
			</constraints>
			<competencies>
				<string>object-26</string>
				<string>object-27</string>
			</competencies>
		</learningObject>

		<learningObject>
			<duration>10</duration>
			<identifier>Identifier-15</identifier>
			<constraints>
				<string>object-26</string>
				<string>object-22</string>
				<string>object-27</string>
			</constraints>
			<competencies>
				<string>object-28</string>
				<string>object-29</string>
				<string>object-30</string>
			</competencies>
		</learningObject>

		<learningObject>
			<duration>10</duration>
			<identifier>Identifier-16</identifier>
			<constraints>
				<string>object-25</string>
				<string>object-30</string>
				<string>object-29</string>
			</constraints>
			<competencies>
				<string>object-31</string>
			</competencies>
		</learningObject>

		<learningObject>
			<duration>10</duration>
			<identifier>Identifier-17</identifier>
			<constraints>
				<string>object-31</string>
				<string>object-28</string>
			</constraints>
			<competencies>
				<string>object-32</string>
				<string>object-33</string>
				<string>object-34</string>
			</competencies>
		</learningObject>

		<learningObject>
			<duration>10</duration>
			<identifier>Identifier-18</identifier>
			<constraints>
				<string>object-32</string>
				<string>object-34</string>
			</constraints>
			<competencies>
				<string>object-35</string>
				<string>object-36</string>
				<string>object-37</string>
			</competencies>
		</learningObject>

		<learningObject>
			<duration>10</duration>
			<identifier>Identifier-19</identifier>
			<constraints>
				<string>object-35</string>
				<string>object-36</string>
				<string>object-33</string>
			</constraints>
			<competencies>
				<string>object-38</string>
			</competencies>
		</learningObject>

		<learningObject>
			<duration>10</duration>
			<identifier>Identifier-20</identifier>
			<constraints>
				<string>object-38</string>
				<string>object-37</string>
			</constraints>
			<competencies>
				<string>object-39</string>
			</competencies>
		</learningObject>

		<learningObject>
			<duration>10</duration>
			<identifier>Identifier-21</identifier>
			<constraints>
				<string>object-39</string>
			</constraints>
			<competencies>
				<string>object-40</string>
				<string>object-41</string>
				<string>object-42</string>
			</competencies>
		</learningObject>

		<learningObject>
			<duration>10</duration>
			<identifier>Identifier-22</identifier>
			<constraints>
				<string>object-41</string>
				<string>object-42</string>
			</constraints>
			<competencies>
				<string>object-43</string>
				<string>object-44</string>
			</competencies>
		</learningObject>

		<learningObject>
			<duration>10</duration>
			<identifier>Identifier-23</identifier>
			<constraints>
				<string>object-40</string>
			</constraints>
			<competencies>
				<string>object-45</string>
				<string>object-46</string>
				<string>object-47</string>
			</competencies>
		</learningObject>

		<learningObject>
			<duration>10</duration>
			<identifier>Identifier-24</identifier>
			<constraints>
				<string>object-43</string>
				<string>object-47</string>
				<string>object-45</string>
			</constraints>
			<competencies>
				<string>object-48</string>
				<string>object-49</string>
			</competencies>
		</learningObject>

		<learningObject>
			<duration>10</duration>
			<identifier>Identifier-25</identifier>
			<constraints>
				<string>object-46</string>
				<string>object-44</string>
				<string>object-48</string>
			</constraints>
			<competencies>
				<string>object-50</string>
			</competencies>
		</learningObject>

		<learningObject>
			<duration>10</duration>
			<identifier>Identifier-26</identifier>
			<constraints>
				<string>object-49</string>
				<string>object-50</string>
			</constraints>
			<competencies>
				<string>object-51</string>
				<string>object-52</string>
				<string>object-53</string>
			</competencies>
		</learningObject>

		<learningObject>
			<duration>10</duration>
			<identifier>Identifier-27</identifier>
			<constraints>
				<string>object-53</string>
				<string>object-52</string>
				<string>object-51</string>
			</constraints>
			<competencies>
				<string>object-54</string>
				<string>object-55</string>
				<string>object-56</string>
			</competencies>
		</learningObject>

		<learningObject>
			<duration>10</duration>
			<identifier>Identifier-28</identifier>
			<constraints>
				<string>object-55</string>
				<string>object-54</string>
				<string>object-56</string>
			</constraints>
			<competencies>
				<string>object-57</string>
			</competencies>
		</learningObject>

		<learningObject>
			<duration>10</duration>
			<identifier>Identifier-29</identifier>
			<constraints>
				<string>object-57</string>
			</constraints>
			<competencies>
				<string>object-58</string>
			</competencies>
		</learningObject>

		<learningObject>
			<duration>10</duration>
			<identifier>Identifier-30</identifier>
			<constraints>
				<string>object-58</string>
			</constraints>
			<competencies>
				<string>object-59</string>
				<string>object-60</string>
			</competencies>
		</learningObject>

		<learningObject>
			<duration>10</duration>
			<identifier>Identifier-31</identifier>
			<constraints>
				<string>object-60</string>
				<string>object-59</string>
			</constraints>
			<competencies>
				<string>object-61</string>
				<string>object-62</string>
				<string>object-63</string>
			</competencies>
		</learningObject>

		<learningObject>
			<duration>10</duration>
			<identifier>Identifier-32</identifier>
			<constraints>
				<string>object-63</string>
				<string>object-62</string>
			</constraints>
			<competencies>
				<string>object-64</string>
				<string>object-65</string>
			</competencies>
		</learningObject>

		<learningObject>
			<duration>10</duration>
			<identifier>Identifier-33</identifier>
			<constraints>
				<string>object-65</string>
			</constraints>
			<competencies>
				<string>object-66</string>
			</competencies>
		</learningObject>

		<learningObject>
			<duration>10</duration>
			<identifier>Identifier-34</identifier>
			<constraints>
				<string>object-66</string>
				<string>object-61</string>
				<string>object-64</string>
			</constraints>
			<competencies>
				<string>object-67</string>
			</competencies>
		</learningObject>

		<learningObject>
			<duration>10</duration>
			<identifier>Identifier-35</identifier>
			<constraints>
				<string>object-67</string>
			</constraints>
			<competencies>
				<string>object-68</string>
				<string>object-69</string>
				<string>object-70</string>
			</competencies>
		</learningObject>

		<learningObject>
			<duration>10</duration>
			<identifier>Identifier-36</identifier>
			<constraints>
				<string>object-69</string>
				<string>object-70</string>
			</constraints>
			<competencies>
				<string>object-71</string>
			</competencies>
		</learningObject>

		<learningObject>
			<duration>10</duration>
			<identifier>Identifier-37</identifier>
			<constraints>
				<string>object-71</string>
			</constraints>
			<competencies>
				<string>object-72</string>
				<string>object-73</string>
				<string>object-74</string>
			</competencies>
		</learningObject>

		<learningObject>
			<duration>10</duration>
			<identifier>Identifier-38</identifier>
			<constraints>
				<string>object-72</string>
				<string>object-74</string>
				<string>object-68</string>
			</constraints>
			<competencies>
				<string>object-75</string>
				<string>object-76</string>
				<string>object-77</string>
			</competencies>
		</learningObject>

		<learningObject>
			<duration>10</duration>
			<identifier>Identifier-39</identifier>
			<constraints>
				<string>object-75</string>
				<string>object-73</string>
			</constraints>
			<competencies>
				<string>object-78</string>
				<string>object-79</string>
			</competencies>
		</learningObject>
	</learningObjects>
</rules>
